opengeodeweb_back/__init__.py
opengeodeweb_back/app.py
opengeodeweb_back/app_config.py
opengeodeweb_back/geode_functions.py
opengeodeweb_back/py.typed
opengeodeweb_back/test_utils.py
opengeodeweb_back/utils_functions.py
opengeodeweb_back/geode_objects/__init__.py
opengeodeweb_back/geode_objects/geode_brep.py
opengeodeweb_back/geode_objects/geode_cross_section.py
opengeodeweb_back/geode_objects/geode_edged_curve2d.py
opengeodeweb_back/geode_objects/geode_edged_curve3d.py
opengeodeweb_back/geode_objects/geode_graph.py
opengeodeweb_back/geode_objects/geode_grid2d.py
opengeodeweb_back/geode_objects/geode_grid3d.py
opengeodeweb_back/geode_objects/geode_hybrid_solid3d.py
opengeodeweb_back/geode_objects/geode_implicit_cross_section.py
opengeodeweb_back/geode_objects/geode_implicit_structural_model.py
opengeodeweb_back/geode_objects/geode_light_regular_grid2d.py
opengeodeweb_back/geode_objects/geode_light_regular_grid3d.py
opengeodeweb_back/geode_objects/geode_mesh.py
opengeodeweb_back/geode_objects/geode_model.py
opengeodeweb_back/geode_objects/geode_object.py
opengeodeweb_back/geode_objects/geode_point_set2d.py
opengeodeweb_back/geode_objects/geode_point_set3d.py
opengeodeweb_back/geode_objects/geode_polygonal_surface2d.py
opengeodeweb_back/geode_objects/geode_polygonal_surface3d.py
opengeodeweb_back/geode_objects/geode_polyhedral_solid3d.py
opengeodeweb_back/geode_objects/geode_raster_image2d.py
opengeodeweb_back/geode_objects/geode_raster_image3d.py
opengeodeweb_back/geode_objects/geode_regular_grid2d.py
opengeodeweb_back/geode_objects/geode_regular_grid3d.py
opengeodeweb_back/geode_objects/geode_section.py
opengeodeweb_back/geode_objects/geode_solid_mesh3d.py
opengeodeweb_back/geode_objects/geode_structural_model.py
opengeodeweb_back/geode_objects/geode_surface_mesh2d.py
opengeodeweb_back/geode_objects/geode_surface_mesh3d.py
opengeodeweb_back/geode_objects/geode_tetrahedral_solid3d.py
opengeodeweb_back/geode_objects/geode_triangulated_surface2d.py
opengeodeweb_back-5.15.0.dist-info/licenses/LICENSE
opengeodeweb_back-5.15.0.dist-info/METADATA
opengeodeweb_back-5.15.0.dist-info/WHEEL
opengeodeweb_back-5.15.0.dist-info/entry_points.txt
opengeodeweb_back-5.15.0.dist-info/top_level.txt
opengeodeweb_back-5.15.0.dist-info/RECORD
