Metadata-Version: 2.4
Name: OpenGeodeWeb-Back
Version: 5.15.0
Summary: OpenGeodeWeb-Back is an open source framework that proposes handy python functions and wrappers for the OpenGeode ecosystem
Author-email: Geode-solutions <team-web@geode-solutions.com>
Project-URL: Homepage, https://github.com/Geode-solutions/OpenGeodeWeb-Back
Project-URL: Bug Tracker, https://github.com/Geode-solutions/OpenGeodeWeb-Back/issues
Classifier: Programming Language :: Python :: 3
Classifier: License :: OSI Approved :: MIT License
Classifier: Operating System :: OS Independent
Requires-Python: <3.13,>=3.9
License-File: LICENSE
Requires-Dist: asgiref>=3
Requires-Dist: blinker>=1
Requires-Dist: click>=8
Requires-Dist: flask[async]>=3
Requires-Dist: flask-cors==6.0.1
Requires-Dist: geode-common==33.11.3
Requires-Dist: geode-viewables==3.3.2
Requires-Dist: itsdangerous>=2
Requires-Dist: jinja2>=3
Requires-Dist: markupsafe>=3
Requires-Dist: opengeode-core==15.30.4
Requires-Dist: opengeode-geosciences==9.5.5
Requires-Dist: opengeode-geosciencesio==5.8.6
Requires-Dist: opengeode-inspector==6.8.6
Requires-Dist: opengeode-io==7.4.6
Requires-Dist: werkzeug==3.1.2
Requires-Dist: opengeodeweb-microservice==1.*,>=1.0.12
Dynamic: license-file
